[{"__symbolic":"module","version":4,"metadata":{"FsDatepickerModule":{"__symbolic":"class","decorators":[{"__symbolic":"call","expression":{"__symbolic":"reference","module":"@angular/core","name":"NgModule","line":11,"character":1},"arguments":[{"imports":[{"__symbolic":"reference","module":"@angular/common","name":"CommonModule","line":13,"character":4},{"__symbolic":"reference","module":"@angular/forms","name":"FormsModule","line":14,"character":4},{"__symbolic":"reference","module":"@firestitch/common","name":"FsCommonModule","line":15,"character":4},{"__symbolic":"reference","module":"@angular/material","name":"MatButtonModule","line":16,"character":4},{"__symbolic":"reference","module":"@angular/material","name":"MatIconModule","line":17,"character":4}],"exports":[{"__symbolic":"reference","module":"./fsdatepicker.directive","name":"FsDatepickerDirective","line":20,"character":4}],"entryComponents":[{"__symbolic":"reference","module":"./fsdatepickerdialog.component","name":"FsDatepickerDialogComponent","line":23,"character":4}],"declarations":[{"__symbolic":"reference","module":"./fsdatepicker.directive","name":"FsDatepickerDirective","line":26,"character":4},{"__symbolic":"reference","module":"./fsdatepickerdialog.component","name":"FsDatepickerDialogComponent","line":27,"character":4},{"__symbolic":"reference","module":"./fsisscroll.directive","name":"FsIsscrollDirective","line":28,"character":4}],"providers":[{"__symbolic":"reference","module":"./fsdatepickerdialogfactory.service","name":"FsDatepickerDialogFactory","line":31,"character":4}]}]}],"statics":{"forRoot":{"__symbolic":"function","parameters":[],"value":{"ngModule":{"__symbolic":"reference","name":"FsDatepickerModule"},"providers":[{"__symbolic":"reference","module":"./fsdatepickerdialogfactory.service","name":"FsDatepickerDialogFactory","line":38,"character":18}]}}}}}}]